[
  {
    "_id": "69dfd59e5765144ac939b595",
    "bus_number": "GJ01BT1001",
    "bus_name": "TMS Swiftline",
    "bus_category": "route",
    "bus_type": "AC Seater",
    "layout_type": "seater",
    "total_seats": 32,
    "status": "Active",
    "__v": 0,
    "createdAt": "2026-04-15T18:14:54.715Z",
    "updatedAt": "2026-04-15T18:14:54.715Z"
  },
  {
    "_id": "69dfd59e5765144ac939b596",
    "bus_number": "GJ01BT1002",
    "bus_name": "TMS Highway King",
    "bus_category": "route",
    "bus_type": "Non-AC Seater",
    "layout_type": "seater",
    "total_seats": 30,
    "status": "Active",
    "__v": 0,
    "createdAt": "2026-04-15T18:14:54.715Z",
    "updatedAt": "2026-04-15T18:14:54.715Z"
  },
  {
    "_id": "69dfd59e5765144ac939b597",
    "bus_number": "GJ01BT1003",
    "bus_name": "TMS Express Star",
    "bus_category": "route",
    "bus_type": "AC Sleeper",
    "layout_type": "sleeper",
    "total_seats": 28,
    "status": "Active",
    "__v": 0,
    "createdAt": "2026-04-15T18:14:54.715Z",
    "updatedAt": "2026-04-15T18:14:54.715Z"
  },
  {
    "_id": "69dfd59e5765144ac939b598",
    "bus_number": "GJ01BT1004",
    "bus_name": "TMS Coastal Ride",
    "bus_category": "route",
    "bus_type": "AC Seater",
    "layout_type": "seater",
    "total_seats": 30,
    "status": "Active",
    "__v": 0,
    "createdAt": "2026-04-15T18:14:54.715Z",
    "updatedAt": "2026-04-15T18:14:54.715Z"
  },
  {
    "_id": "69dfd59e5765144ac939b599",
    "bus_number": "GJ01TT2001",
    "bus_name": "TMS Tour Queen",
    "bus_category": "tour",
    "bus_type": "AC Seater",
    "layout_type": "seater",
    "total_seats": 30,
    "status": "Active",
    "__v": 0,
    "createdAt": "2026-04-15T18:14:54.715Z",
    "updatedAt": "2026-04-15T18:14:54.715Z"
  },
  {
    "_id": "69dfd59e5765144ac939b59a",
    "bus_number": "GJ01TT2002",
    "bus_name": "TMS Heritage Coach",
    "bus_category": "tour",
    "bus_type": "AC Seater",
    "layout_type": "seater",
    "total_seats": 32,
    "status": "Active",
    "__v": 0,
    "createdAt": "2026-04-15T18:14:54.715Z",
    "updatedAt": "2026-04-15T18:14:54.715Z"
  },
  {
    "_id": "69dfd59e5765144ac939b59b",
    "bus_number": "GJ01TT2003",
    "bus_name": "TMS Desert Runner",
    "bus_category": "tour",
    "bus_type": "AC Seater",
    "layout_type": "seater",
    "total_seats": 30,
    "status": "Active",
    "__v": 0,
    "createdAt": "2026-04-15T18:14:54.715Z",
    "updatedAt": "2026-04-15T18:14:54.715Z"
  },
  {
    "_id": "69dfd59e5765144ac939b59c",
    "bus_number": "GJ01TT2004",
    "bus_name": "TMS Pilgrim Special",
    "bus_category": "tour",
    "bus_type": "Non-AC Seater",
    "layout_type": "seater",
    "total_seats": 28,
    "status": "Active",
    "__v": 0,
    "createdAt": "2026-04-15T18:14:54.715Z",
    "updatedAt": "2026-04-15T18:14:54.715Z"
  }
]